serial/__init__.py
serial/serial.py
reverb_serial-2.0.1.dist-info/METADATA
reverb_serial-2.0.1.dist-info/WHEEL
reverb_serial-2.0.1.dist-info/top_level.txt
reverb_serial-2.0.1.dist-info/RECORD
