Metadata-Version: 2.1
Name: reverb-serial
Version: 2.0.1
Summary: A fake serial library for testing purposes
Home-page: https://github.com/TJREVERB/reverb_serial
Author: tjreverb
Author-email: tjreverb@gmail.com
License: GPL
Platform: UNKNOWN
Classifier: Development Status :: 1 - Planning
Classifier: Intended Audience :: Other Audience
Classifier: Topic :: Software Development :: Libraries :: Python Modules
Classifier: Programming Language :: Python :: 3
Requires-Python: >=3.6
